wdu_pdf2md/__init__.py
wdu_pdf2md/wdu_pdf2md_local_python.py
wdu_pdf2md/wdu_pdf2md_runner.py
wdu_pdf2md/wdu_pdf2md_transform.py
wdu_pdf2md/wdu_pdf2md_transform_python.py
dpk_wdu_transform_python-0.2.1.dev1.dist-info/METADATA
dpk_wdu_transform_python-0.2.1.dev1.dist-info/WHEEL
dpk_wdu_transform_python-0.2.1.dev1.dist-info/top_level.txt
dpk_wdu_transform_python-0.2.1.dev1.dist-info/RECORD
